postbot/__init__.py
postbot/db.py
postbot/postbot.py
postbot/util.py
postbot-0.1.4.dist-info/LICENSE
postbot-0.1.4.dist-info/METADATA
postbot-0.1.4.dist-info/WHEEL
postbot-0.1.4.dist-info/top_level.txt
postbot-0.1.4.dist-info/RECORD
