Metadata-Version: 2.1
Name: postbot
Version: 0.1.4
Summary: A simple tool to make posts on Instagram programmatically
Home-page: https://github.com/GAtom22/postbot
Author: Tom G
License: GPLv3
Download-URL: https://github.com/GAtom22/postbot/archive/0.1.4.tar.gz
Keywords: postbot python instagram post automation          marketing promotion bot selenium
Platform: win32
Platform: linux
Platform: linux2
Platform: darwin
Classifier: Development Status :: 4 - Beta
Classifier: Intended Audience :: End Users/Desktop
Classifier: Intended Audience :: Developers
Classifier: Topic :: Software Development :: Build Tools
Classifier: Programming Language :: Python :: 3
Classifier: Programming Language :: Python :: 3.4
Classifier: Programming Language :: Python :: 3.5
Classifier: Programming Language :: Python :: 3.6
Classifier: Programming Language :: Python :: 3.7
Classifier: Programming Language :: Python :: 3.8
Requires-Python: >=3, !=3.0.*, !=3.1.*, !=3.2.*, !=3.3.*
Requires-Dist: mysql-connector-python (>=8.0.22)
Requires-Dist: selenium (>=3.141.0)
